MANIFEST.in
README.md
setup.cfg
setup.py
dyckviz/__init__.py
dyckviz/__main__.py
dyckviz/dyckviz.py
dyckviz.egg-info/PKG-INFO
dyckviz.egg-info/SOURCES.txt
dyckviz.egg-info/dependency_links.txt
dyckviz.egg-info/entry_points.txt
dyckviz.egg-info/requires.txt
dyckviz.egg-info/top_level.txt