Metadata-Version: 1.0
Name: dyckviz
Version: 0.1.0
Summary: Visualization utilities for Dyck words using Young tableaux and combinatorial spider webs.
Home-page: http://github.com/
Author: Orestis Melkonian, Konstantinos Kogkalidis
Author-email: melkon.or@gmail.com, konstantinos@riseup.net
License: UNKNOWN
Platform: any
